README.md
setup.py
KeralaPyApi.egg-info/PKG-INFO
KeralaPyApi.egg-info/SOURCES.txt
KeralaPyApi.egg-info/dependency_links.txt
KeralaPyApi.egg-info/requires.txt
KeralaPyApi.egg-info/top_level.txt
keralabot/__init__.py
keralabot/botapi.py
keralabot/types.py
keralabot/util.py