Metadata-Version: 2.1
Name: KeralaPyApi
Version: 2.3.2020
Summary: Telegram bot api using Python. 
Home-page: https://github.com/KeralaPyApi/KeralaPyApi
Author: Mario
Author-email: keralapyapi@gmail.com
License: GPLv2
Keywords: telegram bot api using python
Platform: UNKNOWN
Classifier: Development Status :: 5 - Production/Stable
Classifier: Programming Language :: Python :: 2
Classifier: Programming Language :: Python :: 2.6
Classifier: Programming Language :: Python :: 2.7
Classifier: Programming Language :: Python :: 3
Classifier: Environment :: Console
Classifier: License :: OSI Approved :: GNU General Public License v2 (GPLv2)
Provides-Extra: json
